<?xml version="1.0" encoding="us-ascii"?>

<world>

    <wall x1="-1.1" y1="-1.5" x2="-1.1" y2="1.5" />
    <wall x1="-1.1" y1="1.5" x2="1.1" y2="1.5" />
    <wall x1="1.1" y1="-1.5" x2="1.1" y2="1.5" />
    <wall x1="-1.1" y1="-1.5" x2="1.1" y2="-1.5" />
    <wall x1="0.671" y1="1.419" x2="0.755" y2="1.366" />
    <wall x1="0.637" y1="-1.126" x2="0.679" y2="-1.036" />
    <wall x1="0.027" y1="-0.044" x2="-0.005" y2="-0.139" />
    <wall x1="-0.499" y1="1.244" x2="-0.558" y2="1.324" />
    <wall x1="-0.204" y1="1.271" x2="-0.106" y2="1.291" />
    <wall x1="-0.944" y1="-0.863" x2="-0.913" y2="-0.768" />
    <wall x1="0.713" y1="-0.483" x2="0.728" y2="-0.581" />
    <wall x1="-1.04" y1="1.058" x2="-0.947" y2="1.021" />
    <wall x1="0.911" y1="0.405" x2="1.01" y2="0.423" />
    <wall x1="-0.627" y1="0.052" x2="-0.629" y2="0.152" />
    <wall x1="0.025" y1="0.463" x2="-0.072" y2="0.486" />
    <wall x1="0.144" y1="0.249" x2="0.06" y2="0.194" />
    <wall x1="-0.565" y1="-0.43" x2="-0.589" y2="-0.528" />
    <wall x1="0.774" y1="-1.366" x2="0.795" y2="-1.268" />
    <wall x1="0.949" y1="0.713" x2="1.005" y2="0.63" />
    <wall x1="-0.568" y1="1.055" x2="-0.492" y2="0.989" />
    <wall x1="-0.221" y1="-1.068" x2="-0.217" y2="-0.968" />
    <wall x1="0.334" y1="0.9" x2="0.238" y2="0.927" />
    <wall x1="0.993" y1="-0.607" x2="0.946" y2="-0.518" />
    <wall x1="-0.611" y1="-0.138" x2="-0.598" y2="-0.238" />

    

    <startPositions>
        <pos x="1.0" y="-1.4" w="0.0" />
        <pos x="-1.0" y="-1.4" w="0.0" />
        <pos x="-1.0" y="0.1" w="0.0" />
        <pos x="1.0" y="0.1" w="0.0" />
    </startPositions>


    <feeder id="1" x="0.5" y="1.0" />

</world>
