<?xml version="1.0" encoding="us-ascii"?>

<world>

    <wall x1="-1.1" y1="-1.5" x2="-1.1" y2="1.5" />
    <wall x1="-1.1" y1="1.5" x2="1.1" y2="1.5" />
    <wall x1="1.1" y1="-1.5" x2="1.1" y2="1.5" />
    <wall x1="-1.1" y1="-1.5" x2="1.1" y2="-1.5" />
    <wall x1="0.044" y1="-1.322" x2="0.034" y2="-1.222" />
    <wall x1="0.223" y1="1.08" x2="0.124" y2="1.064" />
    <wall x1="0.528" y1="-1.473" x2="0.495" y2="-1.378" />
    <wall x1="0.826" y1="-1.253" x2="0.827" y2="-1.353" />
    <wall x1="0.072" y1="-0.522" x2="-0.024" y2="-0.495" />
    <wall x1="-0.868" y1="-0.6" x2="-0.892" y2="-0.696" />
    <wall x1="0.176" y1="-0.252" x2="0.083" y2="-0.289" />
    <wall x1="0.864" y1="-0.273" x2="0.925" y2="-0.353" />
    <wall x1="0.818" y1="-0.145" x2="0.916" y2="-0.129" />
    <wall x1="-0.039" y1="1.428" x2="-0.134" y2="1.458" />
    <wall x1="-0.804" y1="-1.042" x2="-0.836" y2="-1.137" />
    <wall x1="0.472" y1="0.315" x2="0.379" y2="0.278" />
    <wall x1="-0.48" y1="0.786" x2="-0.477" y2="0.886" />
    <wall x1="-1.015" y1="0.979" x2="-0.92" y2="1.012" />
    <wall x1="0.748" y1="0.188" x2="0.745" y2="0.288" />
    <wall x1="0.542" y1="-0.919" x2="0.467" y2="-0.852" />
    <wall x1="-0.907" y1="0.808" x2="-0.952" y2="0.719" />
    <wall x1="-0.251" y1="-0.653" x2="-0.155" y2="-0.625" />
    <wall x1="-0.545" y1="-0.055" x2="-0.643" y2="-0.075" />
    <wall x1="-0.034" y1="-1.108" x2="-0.028" y2="-1.208" />
    <wall x1="0.48" y1="1.425" x2="0.535" y2="1.341" />
    <wall x1="-0.954" y1="0.236" x2="-1.053" y2="0.251" />
    <wall x1="-0.34" y1="-0.003" x2="-0.242" y2="-0.021" />
    <wall x1="0.005" y1="1.227" x2="-0.083" y2="1.274" />
    <wall x1="0.23" y1="0.296" x2="0.33" y2="0.289" />
    <wall x1="-0.688" y1="0.04" x2="-0.765" y2="0.103" />
    <wall x1="0.001" y1="-0.736" x2="-0.037" y2="-0.828" />
    <wall x1="-0.102" y1="1.355" x2="-0.002" y2="1.354" />
    <wall x1="-0.321" y1="-1.234" x2="-0.305" y2="-1.332" />
    <wall x1="0.773" y1="0.393" x2="0.674" y2="0.407" />

    <startPositions>
        <pos x="1.0" y="-1.4" w="0.0" />
        <pos x="-1.0" y="-1.4" w="0.0" />
        <pos x="-1.0" y="0.1" w="0.0" />
        <pos x="1.0" y="0.1" w="0.0" />
    </startPositions>


    <feeder id="1" x="0.5" y="1.0" />

</world>
