<?xml version="1.0" encoding="us-ascii"?>

<world>

    <wall x1="-1.1" y1="-1.5" x2="-1.1" y2="1.5" />
    <wall x1="-1.1" y1="1.5" x2="1.1" y2="1.5" />
    <wall x1="1.1" y1="-1.5" x2="1.1" y2="1.5" />
    <wall x1="-1.1" y1="-1.5" x2="1.1" y2="-1.5" />
    <wall x1="0.624" y1="-0.489" x2="0.864" y2="-0.421" />
    <wall x1="0.809" y1="0.125" x2="0.879" y2="0.366" />
    <wall x1="0.138" y1="0.122" x2="0.176" y2="-0.125" />
    <wall x1="0.328" y1="0.18" x2="0.329" y2="0.43" />
    <wall x1="-0.638" y1="-1.115" x2="-0.807" y2="-1.299" />
    <wall x1="-0.47" y1="0.778" x2="-0.227" y2="0.721" />
    <wall x1="-0.193" y1="1.21" x2="-0.098" y2="1.441" />
    <wall x1="0.708" y1="-1.13" x2="0.835" y2="-0.915" />
    <wall x1="0.867" y1="-0.083" x2="0.696" y2="0.099" />
    <wall x1="0.507" y1="0.146" x2="0.614" y2="0.372" />
    <wall x1="-0.495" y1="1.138" x2="-0.678" y2="1.308" />
    <wall x1="0.688" y1="0.997" x2="0.528" y2="1.189" />
    <wall x1="0.261" y1="-0.213" x2="0.039" y2="-0.33" />
    <wall x1="-0.407" y1="-1.373" x2="-0.257" y2="-1.173" />
    <wall x1="-0.277" y1="-0.656" x2="-0.308" y2="-0.904" />
    <wall x1="0.528" y1="-0.691" x2="0.617" y2="-0.924" />
    <wall x1="-0.669" y1="-0.394" x2="-0.886" y2="-0.52" />
    <wall x1="-0.697" y1="0.446" x2="-0.471" y2="0.341" />
    <wall x1="-0.981" y1="-0.053" x2="-0.822" y2="0.14" />
    <wall x1="-0.482" y1="-0.18" x2="-0.29" y2="-0.34" />
    <wall x1="-0.998" y1="-0.954" x2="-0.771" y2="-1.058" />
    <wall x1="-0.42" y1="-1.041" x2="-0.552" y2="-0.829" />
    <wall x1="0.225" y1="-1.291" x2="0.474" y2="-1.263" />
    <wall x1="-0.264" y1="0.198" x2="-0.065" y2="0.047" />
    <wall x1="-0.937" y1="0.623" x2="-0.977" y2="0.87" />
    <wall x1="-0.376" y1="0.44" x2="-0.127" y2="0.417" />
    <wall x1="0.11" y1="1.097" x2="0.253" y2="0.892" />
    <wall x1="-0.844" y1="-0.285" x2="-0.624" y2="-0.166" />
    <wall x1="-0.804" y1="1.061" x2="-0.585" y2="0.941" />
    <wall x1="0.642" y1="0.84" x2="0.421" y2="0.957" />


    <startPositions>
        <pos x="1.0" y="-1.4" w="0.0" />
        <pos x="-1.0" y="-1.4" w="0.0" />
        <pos x="-1.0" y="0.1" w="0.0" />
        <pos x="1.0" y="0.1" w="0.0" />
    </startPositions>


    <feeder id="1" x="0.5" y="1.0" />

</world>
